<?xml version="1.0" encoding="UTF-8"?>
<objects serializationModel="Studio.02.02.00">
	<object class="AudioFile" id="{5c277835-6215-47d9-bcc0-0da37293e608}">
		<property name="assetPath">
			<value>write01.wav</value>
		</property>
		<property name="frequencyInKHz">
			<value>48</value>
		</property>
		<property name="channelCount">
			<value>1</value>
		</property>
		<property name="length">
			<value>0.46839583333333334</value>
		</property>
		<relationship name="masterAssetFolder">
			<destination>{153d040d-58e5-4eb7-b164-64640d98d8fc}</destination>
		</relationship>
	</object>
</objects>
