<?xml version="1.0" encoding="UTF-8"?>
<objects serializationModel="Studio.02.02.00">
	<object class="AudioFile" id="{6694ee26-977f-4367-8bd9-ae8536beb45e}">
		<property name="assetPath">
			<value>629152__holizna__dusty-lofi-melody-loop-88-bpm.wav</value>
		</property>
		<property name="isStreaming">
			<value>true</value>
		</property>
		<property name="frequencyInKHz">
			<value>192</value>
		</property>
		<property name="channelCount">
			<value>2</value>
		</property>
		<property name="length">
			<value>43.636359374999998</value>
		</property>
		<relationship name="masterAssetFolder">
			<destination>{153d040d-58e5-4eb7-b164-64640d98d8fc}</destination>
		</relationship>
	</object>
</objects>
