<?xml version="1.0" encoding="UTF-8"?>
<objects serializationModel="Studio.02.02.00">
	<object class="AudioFile" id="{687fd6a9-bb2d-482a-a235-b8b433e66ccc}">
		<property name="assetPath">
			<value>Belllow 1.wav</value>
		</property>
		<property name="frequencyInKHz">
			<value>96</value>
		</property>
		<property name="channelCount">
			<value>1</value>
		</property>
		<property name="length">
			<value>0.69999999999999996</value>
		</property>
		<relationship name="masterAssetFolder">
			<destination>{153d040d-58e5-4eb7-b164-64640d98d8fc}</destination>
		</relationship>
	</object>
</objects>
