<?xml version="1.0" encoding="UTF-8"?>
<objects serializationModel="Studio.02.02.00">
	<object class="AudioFile" id="{80079f8b-e47f-40fa-985e-6832916cd91c}">
		<property name="assetPath">
			<value>Grater1.wav</value>
		</property>
		<property name="frequencyInKHz">
			<value>48</value>
		</property>
		<property name="channelCount">
			<value>2</value>
		</property>
		<property name="length">
			<value>3.4361458333333332</value>
		</property>
		<relationship name="masterAssetFolder">
			<destination>{153d040d-58e5-4eb7-b164-64640d98d8fc}</destination>
		</relationship>
	</object>
</objects>
